ascii_parser/__init__.py
ascii_parser/__main__.py
ascii_parser/parser.py
ascii_parser-0.1.4.dist-info/entry_points.txt
ascii_parser-0.1.4.dist-info/LICENSE
ascii_parser-0.1.4.dist-info/WHEEL
ascii_parser-0.1.4.dist-info/METADATA
ascii_parser-0.1.4.dist-info/RECORD
